fm_prime/__init__.py
fm_prime/analyze-hyperbolic-patterns.py
fm_prime/analyze-hyperbolic-visual.py
fm_prime/prime.py
fm_prime/primeFractal.py
fm_prime/primeIndex.py
fm_prime/primePlot.py
fm_prime/primeText.py
fm_prime/primeUtils.py
fm_prime/primeUtils_optimized.py
fm_prime/prime_hybrid.py
fm_prime/prime_hyperbolic_optimized.py
fm_prime/prime_optimized.py
fm_prime/textUtils.py
fm_prime/wheel210.py
fm_prime-1.0.9.dist-info/licenses/LICENSE
fm_prime-1.0.9.dist-info/METADATA
fm_prime-1.0.9.dist-info/WHEEL
fm_prime-1.0.9.dist-info/entry_points.txt
fm_prime-1.0.9.dist-info/top_level.txt
fm_prime-1.0.9.dist-info/RECORD
