Metadata-Version: 2.4
Name: fm-prime
Version: 1.0.9
Summary: Comprehensive prime number utilities with multiple algorithms including the novel Hyperbolic Equation Method with intelligent caching
Home-page: https://github.com/faridmasjedi/fm-prime
Author: Farid Masjedi
Author-email: Farid Masjedi <farid.masjedi1985@gmail.com>
Maintainer-email: Farid Masjedi <farid.masjedi1985@gmail.com>
License: MIT
Project-URL: Homepage, https://github.com/faridmasjedi/fm-prime
Project-URL: Documentation, https://github.com/faridmasjedi/fm-prime#readme
Project-URL: Repository, https://github.com/faridmasjedi/fm-prime.git
Project-URL: Bug Tracker, https://github.com/faridmasjedi/fm-prime/issues
Keywords: prime,prime-numbers,primes,primality-test,sieve,eratosthenes,miller-rabin,wheel-factorization,hyperbolic,number-theory,mathematics,cryptography
Classifier: Development Status :: 5 - Production/Stable
Classifier: Intended Audience :: Developers
Classifier: Intended Audience :: Education
Classifier: Intended Audience :: Science/Research
Classifier: Topic :: Scientific/Engineering :: Mathematics
Classifier: Topic :: Software Development :: Libraries :: Python Modules
Classifier: License :: OSI Approved :: MIT License
Classifier: Programming Language :: Python :: 3
Classifier: Programming Language :: Python :: 3.7
Classifier: Programming Language :: Python :: 3.8
Classifier: Programming Language :: Python :: 3.9
Classifier: Programming Language :: Python :: 3.10
Classifier: Programming Language :: Python :: 3.11
Classifier: Operating System :: OS Independent
Requires-Python: >=3.7
License-File: LICENSE
Dynamic: author
Dynamic: home-page
Dynamic: license-file
Dynamic: requires-python
